[{
        "text": "Россия",
        "value": "RU"
    },
    {
        "text": "Беларусь",
        "value": "BY"
    },
    {
        "text": "Кыргызстан ",
        "value": "KR"
    },
    {
        "text": "Таджикистан ",
        "value": "TG"
    },
    {
        "text": "Узбекистан ",
        "value": "UZ"
    },
    {
        "text": "Туркменистан",
        "value": "TR"
    },
    {
        "text": "Молдова",
        "value": "MD"
    },
    {
        "text": "Азербайджан",
        "value": "AZ"
    },
    {
        "text": "Армения",
        "value": "AM"
    },
    {
        "text": "Казахстан",
        "value": "KZ"
    }
]